chargebeecli/__init__.py
chargebeecli/__main__.py
chargebeecli/client/__init__.py
chargebeecli/client/actions.py
chargebeecli/client/actionsImpl.py
chargebeecli/client/resources.py
chargebeecli/commands/__init__.py
chargebeecli/commands/router.py
chargebeecli/commands/groups/__init__.py
chargebeecli/commands/sub_commands/__init__.py
chargebeecli/commands/sub_commands/addon_cmd.py
chargebeecli/commands/sub_commands/address_cmd.py
chargebeecli/commands/sub_commands/card_cmd.py
chargebeecli/commands/sub_commands/comment_cmd.py
chargebeecli/commands/sub_commands/coupon_cmd.py
chargebeecli/commands/sub_commands/coupon_code_cmd.py
chargebeecli/commands/sub_commands/coupon_set_cmd.py
chargebeecli/commands/sub_commands/credit_note_cmd.py
chargebeecli/commands/sub_commands/customer_cmd.py
chargebeecli/commands/sub_commands/event_cmd.py
chargebeecli/commands/sub_commands/gift_cmd.py
chargebeecli/commands/sub_commands/hosted_page_cmd.py
chargebeecli/commands/sub_commands/invoice_cmd.py
chargebeecli/commands/sub_commands/order_cmd.py
chargebeecli/commands/sub_commands/plan_cmd.py
chargebeecli/commands/sub_commands/profile_cmd.py
chargebeecli/commands/sub_commands/promotional_credit_cmd.py
chargebeecli/commands/sub_commands/quote_cmd.py
chargebeecli/commands/sub_commands/subscription_cmd.py
chargebeecli/commands/sub_commands/theme_cmd.py
chargebeecli/commands/sub_commands/transaction_cmd.py
chargebeecli/commands/sub_commands/unbilled_charge_cmd.py
chargebeecli/config/Configuration.py
chargebeecli/config/__init__.py
chargebeecli/config/config_validator.py
chargebeecli/config/default_config.ini
chargebeecli/constants/__init__.py
chargebeecli/constants/constants.py
chargebeecli/constants/error_messages.py
chargebeecli/export/Exporter.py
chargebeecli/export/__init__.py
chargebeecli/formater/__init__.py
chargebeecli/formater/response_formatter.py
chargebeecli/models/__init__.py
chargebeecli/models/models.py
chargebeecli/printer/__init__.py
chargebeecli/printer/printer.py
chargebee_cli-0.0.23.dist-info/LICENSE
chargebee_cli-0.0.23.dist-info/METADATA
chargebee_cli-0.0.23.dist-info/WHEEL
chargebee_cli-0.0.23.dist-info/entry_points.txt
chargebee_cli-0.0.23.dist-info/top_level.txt
chargebee_cli-0.0.23.dist-info/RECORD
